jvp_flash_attention/__init__.py
jvp_flash_attention/jvp_attention.py
jvp_flash_attention-0.11.0.dist-info/METADATA
jvp_flash_attention-0.11.0.dist-info/WHEEL
jvp_flash_attention-0.11.0.dist-info/licenses/LICENSE
jvp_flash_attention-0.11.0.dist-info/RECORD
