Metadata-Version: 2.4
Name: jvp_flash_attention
Version: 0.11.0
Summary: Flash Attention Triton kernel with support for second-order derivatives
Project-URL: Homepage, https://pypi.org/project/jvp_flash_attention/
Project-URL: Repository, https://github.com/amorehead/jvp-flash-attention
Author-email: Alex Morehead <alex.morehead@gmail.edu>
License-Expression: MIT
License-File: LICENSE
Keywords: artificial intelligence,deep learning
Classifier: Development Status :: 4 - Beta
Classifier: Intended Audience :: Developers
Classifier: License :: OSI Approved :: MIT License
Classifier: Programming Language :: Python :: 3.10
Classifier: Topic :: Scientific/Engineering :: Artificial Intelligence
Requires-Python: >=3.10
Requires-Dist: torch>=2.8.0
Requires-Dist: torchvision>=0.23
Provides-Extra: lint
Requires-Dist: pre-commit>=4.3.0; extra == 'lint'
